{
	"brands": null,
	"cacheVersn": 0,
	"defaultIncidentType": "",
	"definitionId": "",
	"description": "",
	"feed": true,
	"fromServerVersion": "",
	"id": "8324b8d4-0889-438b-84fd-a31f9661d054",
	"incidentSamples": null,
	"indicatorSamples": null,
	"instanceIds": null,
	"itemVersion": "",
	"keyTypeMap": {},
	"locked": false,
	"logicalVersion": 0,
	"mapping": {
		"dbot_classification_incident_type_all": {
			"dontMapEventToLabels": true,
			"internalMapping": {
				"First Seen By Source": {
					"simple": "timePublished"
				},
				"Reported By": {
					"simple": "sourceURL"
				},
				"STIX Indicator Name": {
					"simple": "value"
				},
				"Source Original Severity": {
					"simple": "hashtag"
				},
				"Threat Types": {
					"simple": "indicator_type"
				}
			}
		},
		"urlRep": {
			"dontMapEventToLabels": true,
			"internalMapping": {}
		}
	},
	"name": "sample_csvfeed",
	"nameRaw": "sample_csvfeed",
	"packID": "",
	"packName": "",
	"propagationLabels": [
		"all"
	],
	"sourceClassifierId": "",
	"system": false,
	"toServerVersion": "",
	"transformer": {},
	"type": "mapping-incoming",
	"unclassifiedCases": null,
	"version": -1
}