{
	"autorun": false,
	"cacheVersn": 0,
	"closureScript": "",
	"color": "#6200EA",
	"days": 0,
	"daysR": 0,
	"default": false,
	"definitionId": "",
	"detached": false,
	"disabled": false,
	"extractSettings": {
		"fieldCliNameToExtractSettings": {},
		"mode": "Specific"
	},
	"fromServerVersion": "5.5.0",
	"hours": 0,
	"hoursR": 0,
	"id": "Rapid Breach Response",
	"itemVersion": "1.6.38",
	"layout": "Rapid Breach Response",
	"locked": false,
	"name": "Rapid Breach Response",
	"onChangeRepAlg": 0,
	"packID": "MajorBreachesInvestigationandResponse",
	"packName": "Rapid Breach Response",
	"packPropagationLabels": [
		"all"
	],
	"preProcessingScript": "",
	"propagationLabels": [],
	"readonly": false,
	"reputationCalc": 0,
	"system": true,
	"toServerVersion": "",
	"version": -1,
	"weeks": 0,
	"weeksR": 0
}