{
	"cacheVersn": 0,
	"close": {
		"sections": [
			{
				"description": "",
				"fields": [
					{
						"fieldId": "incident_investigationconclusion",
						"isVisible": true
					},
					{
						"fieldId": "incident_gracaseclosureaction",
						"isVisible": true
					},
					{
						"fieldId": "incident_gracloseas",
						"filters": [
							[
								{
									"left": {
										"isContext": true,
										"value": {
											"simple": "gracaseclosureaction"
										}
									},
									"operator": "isEqualString",
									"right": {
										"isContext": false,
										"value": {
											"simple": "closeCase"
										}
									},
									"type": "singleSelect"
								}
							]
						],
						"isVisible": true
					},
					{
						"fieldId": "incident_gracloseasmodelreview",
						"filters": [
							[
								{
									"left": {
										"isContext": true,
										"value": {
											"simple": "gracaseclosureaction"
										}
									},
									"operator": "isEqualString",
									"right": {
										"isContext": false,
										"value": {
											"simple": "modelReviewCase"
										}
									},
									"type": "singleSelect"
								}
							]
						],
						"isVisible": true
					},
					{
						"fieldId": "incident_gracloseasriskmanaged",
						"filters": [
							[
								{
									"left": {
										"isContext": true,
										"value": {
											"simple": "gracaseclosureaction"
										}
									},
									"operator": "isEqualString",
									"right": {
										"isContext": false,
										"value": {
											"simple": "riskManageCase"
										}
									},
									"type": "singleSelect"
								}
							]
						],
						"isVisible": true
					},
					{
						"fieldId": "incident_informedteamtofinetunealert",
						"isVisible": true
					},
					{
						"fieldId": "incident_investigationanalysis",
						"isVisible": true
					},
					{
						"fieldId": "incident_closingnote",
						"isVisible": true
					},
					{
						"fieldId": "incident_anyimpact",
						"filters": [
							[
								{
									"left": {
										"isContext": true,
										"value": {
											"simple": "investigationconclusion"
										}
									},
									"operator": "isEqualString",
									"right": {
										"isContext": false,
										"value": {
											"simple": "True Positive"
										}
									},
									"type": "singleSelect"
								},
								{
									"left": {
										"isContext": true,
										"value": {
											"simple": "gracloseas"
										}
									},
									"operator": "isEqualString",
									"right": {
										"isContext": false,
										"value": {
											"simple": "True Incident"
										}
									},
									"type": "singleSelect"
								}
							]
						],
						"isVisible": true
					},
					{
						"fieldId": "incident_whatwastheimpact",
						"filters": [
							[
								{
									"left": {
										"isContext": true,
										"value": {
											"simple": "anyimpact"
										}
									},
									"operator": "isEqualString",
									"right": {
										"isContext": false,
										"value": {
											"simple": "Yes"
										}
									},
									"type": "singleSelect"
								}
							],
							[
								{
									"left": {
										"isContext": true,
										"value": {
											"simple": "investigationconclusion"
										}
									},
									"operator": "isEqualString",
									"right": {
										"isContext": false,
										"value": {
											"simple": "True Positive"
										}
									},
									"type": "singleSelect"
								},
								{
									"left": {
										"isContext": true,
										"value": {
											"simple": "gracloseas"
										}
									},
									"operator": "isEqualString",
									"right": {
										"isContext": false,
										"value": {
											"simple": "True Incident"
										}
									},
									"type": "singleSelect"
								}
							]
						],
						"isVisible": true
					},
					{
						"fieldId": "incident_imtraised",
						"filters": [
							[
								{
									"left": {
										"isContext": true,
										"value": {
											"simple": "investigationconclusion"
										}
									},
									"operator": "isEqualString",
									"right": {
										"isContext": false,
										"value": {
											"simple": "True Positive"
										}
									},
									"type": "singleSelect"
								},
								{
									"left": {
										"isContext": true,
										"value": {
											"simple": "gracloseas"
										}
									},
									"operator": "isEqualString",
									"right": {
										"isContext": false,
										"value": {
											"simple": "True Incident"
										}
									},
									"type": "singleSelect"
								}
							]
						],
						"isVisible": true
					},
					{
						"fieldId": "incident_imtnumber",
						"filters": [
							[
								{
									"left": {
										"isContext": true,
										"value": {
											"simple": "imtraised"
										}
									},
									"operator": "isEqualString",
									"right": {
										"isContext": false,
										"value": {
											"simple": "Yes"
										}
									},
									"type": "singleSelect"
								}
							],
							[
								{
									"left": {
										"isContext": true,
										"value": {
											"simple": "investigationconclusion"
										}
									},
									"operator": "isEqualString",
									"right": {
										"isContext": false,
										"value": {
											"simple": "True Positive"
										}
									},
									"type": "singleSelect"
								},
								{
									"left": {
										"isContext": true,
										"value": {
											"simple": "gracloseas"
										}
									},
									"operator": "isEqualString",
									"right": {
										"isContext": false,
										"value": {
											"simple": "True Incident"
										}
									},
									"type": "singleSelect"
								}
							]
						],
						"isVisible": true
					},
					{
						"fieldId": "incident_imtcreationdate",
						"filters": [
							[
								{
									"left": {
										"isContext": true,
										"value": {
											"simple": "imtraised"
										}
									},
									"operator": "isEqualString",
									"right": {
										"isContext": false,
										"value": {
											"simple": "Yes"
										}
									},
									"type": "singleSelect"
								}
							],
							[
								{
									"left": {
										"isContext": true,
										"value": {
											"simple": "investigationconclusion"
										}
									},
									"operator": "isEqualString",
									"right": {
										"isContext": false,
										"value": {
											"simple": "True Positive"
										}
									},
									"type": "singleSelect"
								},
								{
									"left": {
										"isContext": true,
										"value": {
											"simple": "gracloseas"
										}
									},
									"operator": "isEqualString",
									"right": {
										"isContext": false,
										"value": {
											"simple": "True Incident"
										}
									},
									"type": "singleSelect"
								}
							]
						],
						"isVisible": true
					},
					{
						"fieldId": "incident_attachment",
						"isVisible": true
					},
					{
						"fieldId": "incident_justificationforacknowledgementslabreached",
						"filters": [
							[
								{
									"left": {
										"isContext": true,
										"value": {
											"simple": "whichslabreached"
										}
									},
									"operator": "isEqualString",
									"right": {
										"isContext": false,
										"value": {
											"simple": "acknowledgementsla"
										}
									},
									"type": "multiSelect"
								},
								{
									"left": {
										"isContext": true,
										"value": {
											"simple": "whichslabreached"
										}
									},
									"operator": "containsGeneral",
									"right": {
										"isContext": false,
										"value": {
											"simple": "acknowledgementsla"
										}
									},
									"type": "multiSelect"
								}
							]
						],
						"isVisible": true
					},
					{
						"fieldId": "incident_justificationfordetectionslabreached",
						"filters": [
							[
								{
									"left": {
										"isContext": true,
										"value": {
											"simple": "whichslabreached"
										}
									},
									"operator": "isEqualString",
									"right": {
										"isContext": false,
										"value": {
											"simple": "detectionsla"
										}
									},
									"type": "multiSelect"
								},
								{
									"left": {
										"isContext": true,
										"value": {
											"simple": "whichslabreached"
										}
									},
									"operator": "containsGeneral",
									"right": {
										"isContext": false,
										"value": {
											"simple": "detectionsla"
										}
									},
									"type": "multiSelect"
								}
							]
						],
						"isVisible": true
					},
					{
						"fieldId": "incident_justificationformitigationslabreached",
						"filters": [
							[
								{
									"left": {
										"isContext": true,
										"value": {
											"simple": "whichslabreached"
										}
									},
									"operator": "isEqualString",
									"right": {
										"isContext": false,
										"value": {
											"simple": "mitigationsla"
										}
									},
									"type": "multiSelect"
								},
								{
									"left": {
										"isContext": true,
										"value": {
											"simple": "whichslabreached"
										}
									},
									"operator": "containsGeneral",
									"right": {
										"isContext": false,
										"value": {
											"simple": "mitigationsla"
										}
									},
									"type": "multiSelect"
								}
							]
						],
						"isVisible": true
					},
					{
						"fieldId": "incident_justificationforclosureslabreached",
						"filters": [
							[
								{
									"left": {
										"isContext": true,
										"value": {
											"simple": "whichslabreached"
										}
									},
									"operator": "isEqualString",
									"right": {
										"isContext": false,
										"value": {
											"simple": "closuresla"
										}
									},
									"type": "multiSelect"
								},
								{
									"left": {
										"isContext": true,
										"value": {
											"simple": "whichslabreached"
										}
									},
									"operator": "containsGeneral",
									"right": {
										"isContext": false,
										"value": {
											"simple": "closuresla"
										}
									},
									"type": "multiSelect"
								}
							]
						],
						"isVisible": true
					}
				],
				"isVisible": true,
				"name": "Basic Information",
				"query": null,
				"queryType": "",
				"readOnly": false,
				"type": ""
			}
		]
	},
	"definitionId": "",
	"description": "",
	"detached": false,
	"details": null,
	"detailsV2": {
		"TypeName": "",
		"tabs": [
			{
				"id": "summary",
				"name": "Legacy Summary",
				"type": "summary"
			},
			{
				"id": "caseinfoid",
				"name": "Incident Info",
				"sections": [
					{
						"displayType": "ROW",
						"h": 2,
						"i": "caseinfoid-ksqmpk4toz-caseinfoid-fce71720-98b0-11e9-97d7-ed26ef9e46c8",
						"isVisible": true,
						"items": [
							{
								"endCol": 2,
								"fieldId": "severity",
								"height": 22,
								"id": "incident-severity-field",
								"index": 0,
								"sectionItemType": "field",
								"startCol": 0
							},
							{
								"dropEffect": "move",
								"endCol": 2,
								"fieldId": "type",
								"height": 22,
								"id": "incident-type-field",
								"index": 1,
								"listId": "caseinfoid-fce71720-98b0-11e9-97d7-ed26ef9e46c8",
								"sectionItemType": "field",
								"startCol": 0
							},
							{
								"endCol": 2,
								"fieldId": "owner",
								"height": 22,
								"id": "incident-owner-field",
								"index": 2,
								"sectionItemType": "field",
								"startCol": 0
							},
							{
								"endCol": 2,
								"fieldId": "dbotcreated",
								"height": 22,
								"id": "dc87b8f0-a783-11ed-b669-f1c6817aceab",
								"index": 3,
								"sectionItemType": "field",
								"startCol": 0
							},
							{
								"dropEffect": "move",
								"endCol": 2,
								"fieldId": "occurred",
								"height": 22,
								"id": "34c7d1f0-a7a0-11ed-b980-a9b1848be7e5",
								"index": 4,
								"listId": "caseinfoid-fce71720-98b0-11e9-97d7-ed26ef9e46c8",
								"sectionItemType": "field",
								"startCol": 0
							},
							{
								"dropEffect": "move",
								"endCol": 2,
								"fieldId": "shift",
								"height": 22,
								"id": "77f25d00-a783-11ed-b669-f1c6817aceab",
								"index": 5,
								"listId": "caseinfoid-ksqmpk4toz-caseinfoid-fce71720-98b0-11e9-97d7-ed26ef9e46c8",
								"sectionItemType": "field",
								"startCol": 0
							},
							{
								"endCol": 2,
								"fieldId": "closetime",
								"height": 22,
								"id": "3e7f4ed0-a7a0-11ed-b980-a9b1848be7e5",
								"index": 6,
								"sectionItemType": "field",
								"startCol": 0
							},
							{
								"endCol": 2,
								"fieldId": "dbottotaltime",
								"height": 22,
								"id": "56a39340-a7a0-11ed-b980-a9b1848be7e5",
								"index": 7,
								"sectionItemType": "field",
								"startCol": 0
							},
							{
								"endCol": 2,
								"fieldId": "threatresponsesla",
								"height": 22,
								"id": "c4d45890-a7a0-11ed-b980-a9b1848be7e5",
								"index": 8,
								"sectionItemType": "field",
								"startCol": 0
							},
							{
								"endCol": 2,
								"fieldId": "dbotmodified",
								"height": 22,
								"id": "ec802360-a7a0-11ed-b980-a9b1848be7e5",
								"index": 9,
								"sectionItemType": "field",
								"startCol": 0
							}
						],
						"maxW": 3,
						"minH": 1,
						"moved": false,
						"name": "Case Details",
						"static": false,
						"w": 1,
						"x": 1,
						"y": 0
					},
					{
						"displayType": "ROW",
						"h": 3,
						"i": "caseinfoid-ksqmpk4toz-caseinfoid-6aabad20-98b1-11e9-97d7-ed26ef9e46c8",
						"maxW": 3,
						"minH": 1,
						"moved": false,
						"name": "Work Plan",
						"static": false,
						"type": "workplan",
						"w": 1,
						"x": 0,
						"y": 2
					},
					{
						"displayType": "ROW",
						"h": 2,
						"hideName": false,
						"i": "caseinfoid-ksqmpk4toz-caseinfoid-7717e580-9bed-11e9-9a3f-8b4b2158e260",
						"maxW": 3,
						"minH": 1,
						"moved": false,
						"name": "Team Members",
						"static": false,
						"type": "team",
						"w": 1,
						"x": 1,
						"y": 9
					},
					{
						"displayType": "ROW",
						"h": 2,
						"i": "caseinfoid-ksqmpk4toz-caseinfoid-7ce69dd0-a07f-11e9-936c-5395a1acf11e",
						"maxW": 3,
						"minH": 1,
						"moved": false,
						"name": "Indicators",
						"query": "",
						"queryType": "input",
						"static": false,
						"type": "indicators",
						"w": 3,
						"x": 0,
						"y": 7
					},
					{
						"h": 2,
						"i": "caseinfoid-ksqmpk4toz-caseinfoid-329d3a80-a784-11ed-b669-f1c6817aceab",
						"items": [],
						"maxW": 3,
						"minH": 1,
						"moved": false,
						"name": "To-Do Tasks",
						"query": null,
						"static": false,
						"type": "todoTasks",
						"w": 1,
						"x": 0,
						"y": 5
					},
					{
						"displayType": "ROW",
						"h": 2,
						"hideName": false,
						"i": "caseinfoid-ksqmpk4toz-caseinfoid-931c3190-a789-11ed-b669-f1c6817aceab",
						"items": [
							{
								"args": {},
								"buttonClass": "error",
								"dropEffect": "move",
								"endCol": 2,
								"fieldId": "",
								"height": 44,
								"id": "d5457310-a789-11ed-b669-f1c6817aceab",
								"index": 0,
								"listId": "caseinfoid-931c3190-a789-11ed-b669-f1c6817aceab",
								"name": "Lets Get Started !",
								"scriptId": "9cc268a9-63b2-4d77-8fd4-4652b9784714",
								"sectionItemType": "button",
								"startCol": 0
							},
							{
								"args": {},
								"buttonClass": "warning",
								"endCol": 2,
								"fieldId": "",
								"height": 44,
								"id": "fa4d6e10-a789-11ed-b669-f1c6817aceab",
								"index": 1,
								"name": "Link Incidents",
								"scriptId": "Builtin|||linkIncidents",
								"sectionItemType": "button",
								"startCol": 0
							},
							{
								"args": {},
								"endCol": 2,
								"fieldId": "",
								"height": 44,
								"id": "44b017f0-a78a-11ed-b669-f1c6817aceab",
								"index": 2,
								"name": "Generate Summary Report",
								"scriptId": "32fc6dc8-0bdf-4870-84f6-3c20665107cf",
								"sectionItemType": "button",
								"startCol": 0
							},
							{
								"args": {},
								"buttonClass": "success",
								"endCol": 2,
								"fieldId": "",
								"height": 44,
								"id": "6a6b5d60-a78a-11ed-b669-f1c6817aceab",
								"index": 3,
								"name": "Assign to Me",
								"scriptId": "49116bac-a1ba-4202-8978-0b3119216fec",
								"sectionItemType": "button",
								"startCol": 0
							}
						],
						"maxW": 3,
						"minH": 1,
						"moved": false,
						"name": "Quick Section",
						"static": false,
						"w": 1,
						"x": 0,
						"y": 0
					},
					{
						"displayType": "ROW",
						"h": 3,
						"hideName": false,
						"i": "caseinfoid-ksqmpk4toz-caseinfoid-bd31b950-a79d-11ed-b980-a9b1848be7e5",
						"items": [
							{
								"dropEffect": "move",
								"endCol": 2,
								"fieldId": "gracase",
								"height": 22,
								"id": "41269250-a7a6-11ed-b980-a9b1848be7e5",
								"index": 0,
								"listId": "caseinfoid-bd31b950-a79d-11ed-b980-a9b1848be7e5",
								"sectionItemType": "field",
								"startCol": 0
							},
							{
								"endCol": 2,
								"fieldId": "gracaseownerid",
								"height": 22,
								"id": "711c12d0-a79e-11ed-b980-a9b1848be7e5",
								"index": 1,
								"sectionItemType": "field",
								"startCol": 0
							},
							{
								"endCol": 2,
								"fieldId": "gracaseentity",
								"height": 22,
								"id": "52a129e0-b28d-11ed-8102-cbfcd5838b40",
								"index": 2,
								"sectionItemType": "field",
								"startCol": 0
							},
							{
								"dropEffect": "move",
								"endCol": 2,
								"fieldId": "gracaseentityid",
								"height": 22,
								"id": "786d3e10-a79e-11ed-b980-a9b1848be7e5",
								"index": 3,
								"listId": "caseinfoid-bd31b950-a79d-11ed-b980-a9b1848be7e5",
								"sectionItemType": "field",
								"startCol": 0
							},
							{
								"dropEffect": "move",
								"endCol": 2,
								"fieldId": "gracaseentitytypeid",
								"height": 22,
								"id": "0ef69f90-b28d-11ed-8102-cbfcd5838b40",
								"index": 4,
								"listId": "caseinfoid-bd31b950-a79d-11ed-b980-a9b1848be7e5",
								"sectionItemType": "field",
								"startCol": 0
							},
							{
								"endCol": 2,
								"fieldId": "gracaseownername",
								"height": 22,
								"id": "565b2c00-b28a-11ed-8102-cbfcd5838b40",
								"index": 5,
								"sectionItemType": "field",
								"startCol": 0
							},
							{
								"dropEffect": "move",
								"endCol": 2,
								"fieldId": "gracaseopendate",
								"height": 22,
								"id": "4888ad80-a7a6-11ed-b980-a9b1848be7e5",
								"index": 6,
								"listId": "caseinfoid-bd31b950-a79d-11ed-b980-a9b1848be7e5",
								"sectionItemType": "field",
								"startCol": 0
							},
							{
								"dropEffect": "move",
								"endCol": 2,
								"fieldId": "gracaseriskdate",
								"height": 22,
								"id": "60583d60-b28a-11ed-8102-cbfcd5838b40",
								"index": 7,
								"listId": "caseinfoid-bd31b950-a79d-11ed-b980-a9b1848be7e5",
								"sectionItemType": "field",
								"startCol": 0
							},
							{
								"endCol": 2,
								"fieldId": "gracaseriskscore",
								"height": 22,
								"id": "5dfce840-b28a-11ed-8102-cbfcd5838b40",
								"index": 8,
								"sectionItemType": "field",
								"startCol": 0
							},
							{
								"endCol": 2,
								"fieldId": "gracasestatus",
								"height": 22,
								"id": "61ab2810-a7a6-11ed-b980-a9b1848be7e5",
								"index": 9,
								"sectionItemType": "field",
								"startCol": 0
							},
							{
								"dropEffect": "move",
								"endCol": 4,
								"fieldId": "gracaseanomalydetails",
								"height": 106,
								"id": "e3c54b70-a79f-11ed-b980-a9b1848be7e5",
								"index": 10,
								"listId": "caseinfoid-bd31b950-a79d-11ed-b980-a9b1848be7e5",
								"sectionItemType": "field",
								"startCol": 0
							}
						],
						"maxW": 3,
						"minH": 1,
						"moved": false,
						"name": "GRA Details",
						"static": false,
						"w": 2,
						"x": 1,
						"y": 2
					},
					{
						"h": 2,
						"i": "caseinfoid-ksqmpk4toz-caseinfoid-000396e0-a79e-11ed-b980-a9b1848be7e5",
						"items": [],
						"maxW": 3,
						"minH": 1,
						"moved": false,
						"name": "War Room Entries",
						"query": null,
						"queryType": "warRoomFilter",
						"static": false,
						"type": "invTimeline",
						"w": 1,
						"x": 0,
						"y": 9
					},
					{
						"h": 2,
						"i": "caseinfoid-ksqmpk4toz-caseinfoid-afb528b0-a79e-11ed-b980-a9b1848be7e5",
						"items": [],
						"maxW": 3,
						"minH": 1,
						"moved": false,
						"name": "Notes",
						"static": false,
						"type": "notes",
						"w": 2,
						"x": 1,
						"y": 5
					},
					{
						"displayType": "ROW",
						"h": 2,
						"hideName": false,
						"i": "caseinfoid-ksqmpk4toz-caseinfoid-ff2b69e0-a79e-11ed-b980-a9b1848be7e5",
						"items": [
							{
								"endCol": 2,
								"fieldId": "gracaseanomalydetails",
								"height": 106,
								"id": "3f391e60-a79f-11ed-b980-a9b1848be7e5",
								"index": 0,
								"sectionItemType": "field",
								"startCol": 0
							},
							{
								"endCol": 2,
								"fieldId": "gracaseopendate",
								"height": 22,
								"id": "4b5b0b90-a79f-11ed-b980-a9b1848be7e5",
								"index": 1,
								"sectionItemType": "field",
								"startCol": 0
							},
							{
								"endCol": 2,
								"fieldId": "gracaseentityid",
								"height": 22,
								"id": "5666f4e0-a79f-11ed-b980-a9b1848be7e5",
								"index": 2,
								"sectionItemType": "field",
								"startCol": 0
							},
							{
								"endCol": 2,
								"fieldId": "gracaseriskscore",
								"height": 22,
								"id": "6f333920-a79f-11ed-b980-a9b1848be7e5",
								"index": 3,
								"sectionItemType": "field",
								"startCol": 0
							}
						],
						"maxW": 3,
						"minH": 1,
						"moved": false,
						"name": "Investigation Details",
						"static": false,
						"w": 1,
						"x": 2,
						"y": 9
					},
					{
						"displayType": "CARD",
						"h": 2,
						"hideName": false,
						"i": "caseinfoid-7dd01da3-2570-11ee-8255-07b673d2d52a",
						"items": [
							{
								"endCol": 2,
								"fieldId": "acknowledgementsla",
								"height": 53,
								"id": "0141b360-24a9-11ee-8bcf-b7aa2c78ef4e",
								"index": 0,
								"sectionItemType": "field",
								"startCol": 0
							},
							{
								"dropEffect": "move",
								"endCol": 2,
								"fieldId": "detectionsla",
								"height": 53,
								"id": "e342df90-a7a0-11ed-b980-a9b1848be7e5",
								"index": 1,
								"listId": "caseinfoid-7dd01da3-2570-11ee-8255-07b673d2d52a",
								"sectionItemType": "field",
								"startCol": 0
							},
							{
								"dropEffect": "move",
								"endCol": 2,
								"fieldId": "mitigation",
								"height": 53,
								"id": "a972ea80-a7a0-11ed-b980-a9b1848be7e5",
								"index": 2,
								"listId": "caseinfoid-7dd01da3-2570-11ee-8255-07b673d2d52a",
								"sectionItemType": "field",
								"startCol": 0
							},
							{
								"dropEffect": "move",
								"endCol": 2,
								"fieldId": "closuresla",
								"height": 53,
								"id": "9d16da80-a7a0-11ed-b980-a9b1848be7e5",
								"index": 3,
								"listId": "caseinfoid-7dd01da3-2570-11ee-8255-07b673d2d52a",
								"sectionItemType": "field",
								"startCol": 0
							}
						],
						"maxW": 3,
						"minH": 1,
						"moved": false,
						"name": "SLA Status",
						"static": false,
						"w": 1,
						"x": 2,
						"y": 0
					}
				],
				"type": "custom"
			},
			{
				"hidden": false,
				"id": "xhvsnnqtsj",
				"name": "GRA Details",
				"sections": [
					{
						"displayType": "ROW",
						"h": 4,
						"hideName": false,
						"i": "caseinfoid-ade5d830-a7a4-11ed-b980-a9b1848be7e5",
						"items": [
							{
								"endCol": 2,
								"fieldId": "gracase",
								"height": 22,
								"id": "afcfa6d0-a7a4-11ed-b980-a9b1848be7e5",
								"index": 0,
								"sectionItemType": "field",
								"startCol": 0
							},
							{
								"endCol": 2,
								"fieldId": "gracaseentity",
								"height": 22,
								"id": "b2809600-a7a4-11ed-b980-a9b1848be7e5",
								"index": 1,
								"sectionItemType": "field",
								"startCol": 0
							},
							{
								"dropEffect": "move",
								"endCol": 2,
								"fieldId": "gracaseentityid",
								"height": 22,
								"id": "d06dc840-b28a-11ed-8102-cbfcd5838b40",
								"index": 2,
								"listId": "caseinfoid-ade5d830-a7a4-11ed-b980-a9b1848be7e5",
								"sectionItemType": "field",
								"startCol": 0
							},
							{
								"dropEffect": "move",
								"endCol": 2,
								"fieldId": "gracaseentitytypeid",
								"height": 22,
								"id": "21c25470-b28d-11ed-8102-cbfcd5838b40",
								"index": 3,
								"listId": "caseinfoid-ade5d830-a7a4-11ed-b980-a9b1848be7e5",
								"sectionItemType": "field",
								"startCol": 0
							},
							{
								"endCol": 2,
								"fieldId": "gracaseopendate",
								"height": 22,
								"id": "b5589530-a7a4-11ed-b980-a9b1848be7e5",
								"index": 4,
								"sectionItemType": "field",
								"startCol": 0
							},
							{
								"endCol": 2,
								"fieldId": "gracaseriskdate",
								"height": 22,
								"id": "96ae26e0-b28a-11ed-8102-cbfcd5838b40",
								"index": 5,
								"sectionItemType": "field",
								"startCol": 0
							},
							{
								"dropEffect": "move",
								"endCol": 2,
								"fieldId": "gracaseriskscore",
								"height": 22,
								"id": "c20d4c80-a7a4-11ed-b980-a9b1848be7e5",
								"index": 6,
								"listId": "caseinfoid-ade5d830-a7a4-11ed-b980-a9b1848be7e5",
								"sectionItemType": "field",
								"startCol": 0
							},
							{
								"endCol": 2,
								"fieldId": "gracaseownername",
								"height": 22,
								"id": "b8f67c70-a7a4-11ed-b980-a9b1848be7e5",
								"index": 7,
								"sectionItemType": "field",
								"startCol": 0
							},
							{
								"endCol": 2,
								"fieldId": "gracaseownertype",
								"height": 22,
								"id": "d98d3aa0-a7a4-11ed-b980-a9b1848be7e5",
								"index": 8,
								"sectionItemType": "field",
								"startCol": 0
							},
							{
								"endCol": 2,
								"fieldId": "gracasestatus",
								"height": 22,
								"id": "9a196ff0-b28b-11ed-8102-cbfcd5838b40",
								"index": 9,
								"sectionItemType": "field",
								"startCol": 0
							},
							{
								"dropEffect": "move",
								"endCol": 2,
								"fieldId": "gracaseweblink",
								"height": 22,
								"id": "c4af4790-a7a4-11ed-b980-a9b1848be7e5",
								"index": 10,
								"listId": "caseinfoid-ade5d830-a7a4-11ed-b980-a9b1848be7e5",
								"sectionItemType": "field",
								"startCol": 0
							},
							{
								"dropEffect": "move",
								"endCol": 6,
								"fieldId": "gracaseanomalydetails",
								"height": 106,
								"id": "b11916c0-a7a4-11ed-b980-a9b1848be7e5",
								"index": 11,
								"listId": "caseinfoid-ade5d830-a7a4-11ed-b980-a9b1848be7e5",
								"sectionItemType": "field",
								"startCol": 0
							}
						],
						"maxW": 3,
						"minH": 1,
						"moved": false,
						"name": "GRA Alert Details",
						"static": false,
						"w": 3,
						"x": 0,
						"y": 0
					}
				],
				"type": "custom"
			},
			{
				"hidden": false,
				"id": "welklzxtsc",
				"name": "Investigation",
				"sections": [
					{
						"h": 2,
						"i": "caseinfoid-fec43f70-a7a5-11ed-b980-a9b1848be7e5",
						"items": [],
						"maxW": 3,
						"minH": 1,
						"moved": false,
						"name": " Indicators",
						"query": "reputation:Bad or reputation:Suspicious",
						"queryType": "input",
						"static": false,
						"type": "indicators",
						"w": 3,
						"x": 0,
						"y": 0
					},
					{
						"h": 2,
						"i": "caseinfoid-3450d540-b2b9-11ed-a624-e5831618c9c0",
						"items": [],
						"maxW": 3,
						"minH": 1,
						"moved": false,
						"name": "Linked Incidents",
						"static": false,
						"type": "linkedIncidents",
						"w": 3,
						"x": 0,
						"y": 2
					},
					{
						"h": 2,
						"i": "caseinfoid-56a7ba00-b2b9-11ed-a624-e5831618c9c0",
						"items": [],
						"maxW": 3,
						"minH": 1,
						"moved": false,
						"name": "Evidence / Report",
						"static": false,
						"type": "evidence",
						"w": 3,
						"x": 0,
						"y": 4
					},
					{
						"h": 4,
						"i": "caseinfoid-775f1f90-b2b9-11ed-a624-e5831618c9c0",
						"items": [],
						"maxW": 3,
						"minH": 1,
						"moved": false,
						"name": "Notes",
						"static": false,
						"type": "notes",
						"w": 3,
						"x": 0,
						"y": 6
					}
				],
				"type": "custom"
			},
			{
				"hidden": false,
				"id": "wugdzwmhze",
				"name": "Reference",
				"sections": [
					{
						"displayType": "CARD",
						"h": 1,
						"hideItemTitleOnlyOne": true,
						"hideName": false,
						"i": "caseinfoid-qlo4sipnul-caseinfoid-ca217b40-f77c-11ec-9f57-717cb29f6f4f",
						"items": [
							{
								"dropEffect": "move",
								"endCol": 6,
								"fieldId": "playbookrepository",
								"height": 22,
								"id": "e7bc3780-f77c-11ec-9f57-717cb29f6f4f",
								"index": 0,
								"listId": "caseinfoid-ca217b40-f77c-11ec-9f57-717cb29f6f4f",
								"sectionItemType": "field",
								"startCol": 0
							},
							{
								"endCol": 2,
								"fieldId": "mitreattckmatrix",
								"height": 22,
								"id": "057223e0-2f57-11ed-8f0a-17d3255d2eb6",
								"index": 1,
								"sectionItemType": "field",
								"startCol": 0
							},
							{
								"endCol": 2,
								"fieldId": "mitred3fendmatrix",
								"height": 22,
								"id": "075fc310-2f57-11ed-8f0a-17d3255d2eb6",
								"index": 2,
								"sectionItemType": "field",
								"startCol": 0
							}
						],
						"maxW": 3,
						"minH": 1,
						"moved": false,
						"name": "Knowledge Repository Link",
						"static": false,
						"w": 3,
						"x": 0,
						"y": 0
					},
					{
						"displayType": "ROW",
						"h": 6,
						"hideItemTitleOnlyOne": true,
						"hideName": false,
						"i": "caseinfoid-qlo4sipnul-caseinfoid-f7cf3500-f77c-11ec-9f57-717cb29f6f4f",
						"items": [
							{
								"dropEffect": "move",
								"endCol": 6,
								"fieldId": "prioritymatrix",
								"height": 106,
								"id": "19762ab0-f77d-11ec-9f57-717cb29f6f4f",
								"index": 0,
								"listId": "caseinfoid-f7cf3500-f77c-11ec-9f57-717cb29f6f4f",
								"sectionItemType": "field",
								"startCol": 0
							}
						],
						"maxW": 3,
						"minH": 1,
						"moved": false,
						"name": "Priority Matrix (guide for calculating alert severity)",
						"static": false,
						"w": 3,
						"x": 0,
						"y": 1
					}
				],
				"type": "custom"
			},
			{
				"hidden": false,
				"id": "ksqmpk4toz",
				"name": "Report summary ",
				"sections": [
					{
						"displayType": "ROW",
						"h": 4,
						"hideItemTitleOnlyOne": true,
						"hideName": false,
						"i": "ksqmpk4toz-caseinfoid-ksqmpk4toz-caseinfoid-ksqmpk4toz-caseinfoid-a128b810-a786-11ed-b669-f1c6817aceab",
						"items": [
							{
								"dropEffect": "move",
								"endCol": 6,
								"fieldId": "investigationanalysis",
								"height": 44,
								"id": "f00614a0-a786-11ed-b669-f1c6817aceab",
								"index": 0,
								"listId": "caseinfoid-a128b810-a786-11ed-b669-f1c6817aceab",
								"sectionItemType": "field",
								"startCol": 0
							}
						],
						"maxW": 3,
						"minH": 1,
						"moved": false,
						"name": "Investigation Analysis",
						"static": false,
						"w": 3,
						"x": 0,
						"y": 4
					},
					{
						"displayType": "ROW",
						"h": 2,
						"hideItemTitleOnlyOne": true,
						"hideName": false,
						"i": "ksqmpk4toz-caseinfoid-ksqmpk4toz-caseinfoid-ksqmpk4toz-caseinfoid-3266e0e0-a787-11ed-b669-f1c6817aceab",
						"items": [
							{
								"dropEffect": "move",
								"endCol": 6,
								"fieldId": "closingnote",
								"height": 106,
								"id": "5f83f360-a787-11ed-b669-f1c6817aceab",
								"index": 0,
								"listId": "caseinfoid-3266e0e0-a787-11ed-b669-f1c6817aceab",
								"sectionItemType": "field",
								"startCol": 0
							}
						],
						"maxW": 3,
						"minH": 1,
						"moved": false,
						"name": "Closing Note",
						"static": false,
						"w": 3,
						"x": 0,
						"y": 8
					},
					{
						"displayType": "CARD",
						"h": 5,
						"hideName": false,
						"i": "ksqmpk4toz-caseinfoid-ksqmpk4toz-caseinfoid-ksqmpk4toz-caseinfoid-6cdd9d40-a787-11ed-b669-f1c6817aceab",
						"items": [
							{
								"endCol": 2,
								"fieldId": "investigationconclusion",
								"height": 53,
								"id": "d39da160-a787-11ed-b669-f1c6817aceab",
								"index": 0,
								"sectionItemType": "field",
								"startCol": 0
							},
							{
								"endCol": 5,
								"fieldId": "gracaseclosureaction",
								"height": 53,
								"id": "3275f440-b439-11ed-9634-a75ab79cd527",
								"index": 1,
								"sectionItemType": "field",
								"startCol": 0
							},
							{
								"endCol": 2,
								"fieldId": "gracloseas",
								"filters": [
									[
										{
											"id": 0,
											"ignoreCase": false,
											"left": {
												"isContext": true,
												"value": {
													"simple": "gracaseclosureaction"
												}
											},
											"operator": "isEqualString",
											"right": {
												"isContext": false,
												"value": {
													"simple": "closeCase"
												}
											},
											"type": "singleSelect"
										}
									]
								],
								"height": 53,
								"id": "46b33a80-b439-11ed-9634-a75ab79cd527",
								"index": 2,
								"sectionItemType": "field",
								"startCol": 0
							},
							{
								"endCol": 2,
								"fieldId": "gracloseasmodelreview",
								"filters": [
									[
										{
											"id": 0,
											"ignoreCase": false,
											"left": {
												"isContext": true,
												"value": {
													"simple": "gracaseclosureaction"
												}
											},
											"operator": "isEqualString",
											"right": {
												"isContext": false,
												"value": {
													"simple": "modelReviewCase"
												}
											},
											"type": "singleSelect"
										}
									]
								],
								"height": 53,
								"id": "494d1f40-b439-11ed-9634-a75ab79cd527",
								"index": 3,
								"sectionItemType": "field",
								"startCol": 0
							},
							{
								"endCol": 2,
								"fieldId": "tuninginformation",
								"filters": [
									[
										{
											"ignoreCase": false,
											"left": {
												"isContext": true,
												"value": {
													"simple": "gracloseasmodelreview"
												}
											},
											"operator": "isEqualString",
											"right": {
												"isContext": false,
												"value": {
													"simple": "Tuning Required"
												}
											},
											"type": "singleSelect"
										}
									],
									[
										{
											"ignoreCase": false,
											"left": {
												"isContext": true,
												"value": {
													"simple": "gracaseclosureaction"
												}
											},
											"operator": "isEqualString",
											"right": {
												"isContext": false,
												"value": {
													"simple": "modelReviewCase"
												}
											},
											"type": "singleSelect"
										}
									]
								],
								"height": 53,
								"id": "bf57b690-6f78-11ef-a62b-05e6dbf7066c",
								"index": 4,
								"sectionItemType": "field",
								"startCol": 0
							},
							{
								"endCol": 2,
								"fieldId": "gracloseasriskmanaged",
								"filters": [
									[
										{
											"id": 0,
											"ignoreCase": false,
											"left": {
												"isContext": true,
												"value": {
													"simple": "gracaseclosureaction"
												}
											},
											"operator": "isEqualString",
											"right": {
												"isContext": false,
												"value": {
													"simple": "riskManageCase"
												}
											},
											"type": "singleSelect"
										}
									]
								],
								"height": 53,
								"id": "4b1f6e40-b439-11ed-9634-a75ab79cd527",
								"index": 5,
								"sectionItemType": "field",
								"startCol": 0
							},
							{
								"endCol": 2,
								"fieldId": "imtraised",
								"filters": [
									[
										{
											"id": 0,
											"ignoreCase": false,
											"left": {
												"isContext": true,
												"value": {
													"simple": "investigationconclusion"
												}
											},
											"operator": "isEqualString",
											"right": {
												"isContext": false,
												"value": {
													"simple": "True Positive"
												}
											},
											"type": "singleSelect"
										},
										{
											"id": 1,
											"ignoreCase": false,
											"left": {
												"isContext": true,
												"value": {
													"simple": "gracloseas"
												}
											},
											"operator": "isEqualString",
											"right": {
												"isContext": false,
												"value": {
													"simple": "True Incident"
												}
											},
											"type": "singleSelect"
										}
									]
								],
								"height": 53,
								"id": "1958a270-b43c-11ed-a6b8-2da4d839ab29",
								"index": 6,
								"sectionItemType": "field",
								"startCol": 0
							},
							{
								"dropEffect": "move",
								"endCol": 2,
								"fieldId": "imtnumber",
								"filters": [
									[
										{
											"id": 0,
											"ignoreCase": false,
											"left": {
												"isContext": true,
												"value": {
													"simple": "imtraised"
												}
											},
											"operator": "isEqualString",
											"right": {
												"isContext": false,
												"value": {
													"simple": "Yes"
												}
											},
											"type": "singleSelect"
										}
									],
									[
										{
											"id": 0,
											"ignoreCase": false,
											"left": {
												"isContext": true,
												"value": {
													"simple": "investigationconclusion"
												}
											},
											"operator": "isEqualString",
											"right": {
												"isContext": false,
												"value": {
													"simple": "True Positive"
												}
											},
											"type": "singleSelect"
										},
										{
											"id": 1,
											"ignoreCase": false,
											"left": {
												"isContext": true,
												"value": {
													"simple": "gracloseas"
												}
											},
											"operator": "isEqualString",
											"right": {
												"isContext": false,
												"value": {
													"simple": "True Incident"
												}
											},
											"type": "singleSelect"
										}
									]
								],
								"height": 53,
								"id": "fda6eec0-a788-11ed-b669-f1c6817aceab",
								"index": 7,
								"listId": "caseinfoid-6cdd9d40-a787-11ed-b669-f1c6817aceab",
								"sectionItemType": "field",
								"startCol": 0
							},
							{
								"endCol": 2,
								"fieldId": "imtcreationdate",
								"filters": [
									[
										{
											"id": 0,
											"ignoreCase": false,
											"left": {
												"isContext": true,
												"value": {
													"simple": "imtraised"
												}
											},
											"operator": "isEqualString",
											"right": {
												"isContext": false,
												"value": {
													"simple": "Yes"
												}
											},
											"type": "singleSelect"
										}
									],
									[
										{
											"id": 0,
											"ignoreCase": false,
											"left": {
												"isContext": true,
												"value": {
													"simple": "investigationconclusion"
												}
											},
											"operator": "isEqualString",
											"right": {
												"isContext": false,
												"value": {
													"simple": "True Positive"
												}
											},
											"type": "singleSelect"
										},
										{
											"id": 1,
											"ignoreCase": false,
											"left": {
												"isContext": true,
												"value": {
													"simple": "gracloseas"
												}
											},
											"operator": "isEqualString",
											"right": {
												"isContext": false,
												"value": {
													"simple": "True Incident"
												}
											},
											"type": "singleSelect"
										}
									]
								],
								"height": 53,
								"id": "1beeb6a0-b43c-11ed-a6b8-2da4d839ab29",
								"index": 8,
								"sectionItemType": "field",
								"startCol": 0
							},
							{
								"endCol": 2,
								"fieldId": "imtlocation",
								"filters": [
									[
										{
											"id": 0,
											"ignoreCase": false,
											"left": {
												"isContext": true,
												"value": {
													"simple": "imtraised"
												}
											},
											"operator": "isEqualString",
											"right": {
												"isContext": false,
												"value": {
													"simple": "Yes"
												}
											},
											"type": "singleSelect"
										}
									],
									[
										{
											"id": 0,
											"ignoreCase": false,
											"left": {
												"isContext": true,
												"value": {
													"simple": "investigationconclusion"
												}
											},
											"operator": "isEqualString",
											"right": {
												"isContext": false,
												"value": {
													"simple": "True Positive"
												}
											},
											"type": "singleSelect"
										},
										{
											"id": 1,
											"ignoreCase": false,
											"left": {
												"isContext": true,
												"value": {
													"simple": "gracloseas"
												}
											},
											"operator": "isEqualString",
											"right": {
												"isContext": false,
												"value": {
													"simple": "True Incident"
												}
											},
											"type": "singleSelect"
										}
									]
								],
								"height": 53,
								"id": "0a102820-435b-11ee-858c-f100845740f8",
								"index": 9,
								"sectionItemType": "field",
								"startCol": 0
							},
							{
								"endCol": 2,
								"fieldId": "anyimpact",
								"filters": [
									[
										{
											"id": 0,
											"ignoreCase": false,
											"left": {
												"isContext": true,
												"value": {
													"simple": "investigationconclusion"
												}
											},
											"operator": "isEqualString",
											"right": {
												"isContext": false,
												"value": {
													"simple": "True Positive"
												}
											},
											"type": "singleSelect"
										},
										{
											"id": 1,
											"ignoreCase": false,
											"left": {
												"isContext": true,
												"value": {
													"simple": "gracloseas"
												}
											},
											"operator": "isEqualString",
											"right": {
												"isContext": false,
												"value": {
													"simple": "True Incident"
												}
											},
											"type": "singleSelect"
										}
									]
								],
								"height": 53,
								"id": "49dcee80-a788-11ed-b669-f1c6817aceab",
								"index": 10,
								"sectionItemType": "field",
								"startCol": 0
							},
							{
								"endCol": 2,
								"fieldId": "whatwastheimpact",
								"filters": [
									[
										{
											"id": 0,
											"ignoreCase": false,
											"left": {
												"isContext": true,
												"value": {
													"simple": "anyimpact"
												}
											},
											"operator": "isEqualString",
											"right": {
												"isContext": false,
												"value": {
													"simple": "Yes"
												}
											},
											"type": "singleSelect"
										}
									],
									[
										{
											"id": 0,
											"ignoreCase": false,
											"left": {
												"isContext": true,
												"value": {
													"simple": "investigationconclusion"
												}
											},
											"operator": "isEqualString",
											"right": {
												"isContext": false,
												"value": {
													"simple": "True Positive"
												}
											},
											"type": "singleSelect"
										},
										{
											"id": 1,
											"ignoreCase": false,
											"left": {
												"isContext": true,
												"value": {
													"simple": "gracloseas"
												}
											},
											"operator": "isEqualString",
											"right": {
												"isContext": false,
												"value": {
													"simple": "True Incident"
												}
											},
											"type": "singleSelect"
										}
									]
								],
								"height": 53,
								"id": "4de0ea90-a788-11ed-b669-f1c6817aceab",
								"index": 11,
								"sectionItemType": "field",
								"startCol": 0
							},
							{
								"endCol": 2,
								"fieldId": "informedteamtofinetunealert",
								"height": 53,
								"id": "8617a990-a7aa-11ed-b980-a9b1848be7e5",
								"index": 12,
								"sectionItemType": "field",
								"startCol": 0
							},
							{
								"dropEffect": "move",
								"endCol": 2,
								"fieldId": "dbotclosed",
								"height": 53,
								"id": "2d0cfc50-a788-11ed-b669-f1c6817aceab",
								"index": 13,
								"listId": "caseinfoid-6cdd9d40-a787-11ed-b669-f1c6817aceab",
								"sectionItemType": "field",
								"startCol": 0
							},
							{
								"endCol": 6,
								"fieldId": "justificationforbreachedacknowledgementsla",
								"filters": [
									[
										{
											"ignoreCase": false,
											"left": {
												"isContext": true,
												"value": {
													"simple": "whichslabreached"
												}
											},
											"operator": "isEqualString",
											"right": {
												"isContext": false,
												"value": {
													"simple": "acknowledgementsla"
												}
											},
											"type": "multiSelect"
										},
										{
											"ignoreCase": false,
											"left": {
												"isContext": true,
												"value": {
													"simple": "whichslabreached"
												}
											},
											"operator": "containsGeneral",
											"right": {
												"isContext": false,
												"value": {
													"simple": "acknowledgementsla"
												}
											},
											"type": "multiSelect"
										}
									]
								],
								"height": 53,
								"id": "85930410-e089-11ee-903f-f9579ae2db30",
								"index": 14,
								"sectionItemType": "field",
								"startCol": 0
							},
							{
								"endCol": 6,
								"fieldId": "justificationfordetectionslabreached",
								"filters": [
									[
										{
											"id": 0,
											"ignoreCase": false,
											"left": {
												"isContext": true,
												"value": {
													"simple": "whichslabreached"
												}
											},
											"operator": "isEqualString",
											"right": {
												"isContext": false,
												"value": {
													"simple": "detectionsla"
												}
											},
											"type": "multiSelect"
										},
										{
											"id": 1,
											"ignoreCase": false,
											"left": {
												"isContext": true,
												"value": {
													"simple": "whichslabreached"
												}
											},
											"operator": "containsGeneral",
											"right": {
												"isContext": false,
												"value": {
													"simple": "detectionsla"
												}
											},
											"type": "multiSelect"
										}
									]
								],
								"height": 106,
								"id": "8bf26890-c321-11ed-891f-1937ead4a7b9",
								"index": 15,
								"sectionItemType": "field",
								"startCol": 0
							},
							{
								"endCol": 6,
								"fieldId": "justificationformitigationslabreached",
								"filters": [
									[
										{
											"id": 0,
											"ignoreCase": false,
											"left": {
												"isContext": true,
												"value": {
													"simple": "whichslabreached"
												}
											},
											"operator": "isEqualString",
											"right": {
												"isContext": false,
												"value": {
													"simple": "mitigationsla"
												}
											},
											"type": "multiSelect"
										},
										{
											"id": 1,
											"ignoreCase": false,
											"left": {
												"isContext": true,
												"value": {
													"simple": "whichslabreached"
												}
											},
											"operator": "containsGeneral",
											"right": {
												"isContext": false,
												"value": {
													"simple": "mitigationsla"
												}
											},
											"type": "multiSelect"
										}
									]
								],
								"height": 106,
								"id": "949e8ff0-c321-11ed-891f-1937ead4a7b9",
								"index": 16,
								"sectionItemType": "field",
								"startCol": 0
							},
							{
								"endCol": 6,
								"fieldId": "justificationforclosureslabreached",
								"filters": [
									[
										{
											"id": 0,
											"ignoreCase": false,
											"left": {
												"isContext": true,
												"value": {
													"simple": "whichslabreached"
												}
											},
											"operator": "isEqualString",
											"right": {
												"isContext": false,
												"value": {
													"simple": "closuresla"
												}
											},
											"type": "multiSelect"
										},
										{
											"id": 1,
											"ignoreCase": false,
											"left": {
												"isContext": true,
												"value": {
													"simple": "whichslabreached"
												}
											},
											"operator": "containsGeneral",
											"right": {
												"isContext": false,
												"value": {
													"simple": "closuresla"
												}
											},
											"type": "multiSelect"
										}
									]
								],
								"height": 106,
								"id": "97574750-c321-11ed-891f-1937ead4a7b9",
								"index": 17,
								"sectionItemType": "field",
								"startCol": 0
							},
							{
								"endCol": 2,
								"fieldId": "reviewby",
								"height": 53,
								"id": "664eecc0-a789-11ed-b669-f1c6817aceab",
								"index": 18,
								"sectionItemType": "field",
								"startCol": 0
							},
							{
								"endCol": 2,
								"fieldId": "reviewedby",
								"height": 53,
								"id": "cd926e10-c3eb-11ed-b2f4-43cb48649dfd",
								"index": 18,
								"sectionItemType": "field",
								"startCol": 0
							},
							{
								"endCol": 2,
								"fieldId": "reviewnotes",
								"height": 106,
								"id": "69334800-a789-11ed-b669-f1c6817aceab",
								"index": 19,
								"sectionItemType": "field",
								"startCol": 0
							},
							{
								"endCol": 2,
								"fieldId": "reviewdate",
								"height": 53,
								"id": "e09a5260-a830-11ed-9cf5-7d242b23291a",
								"index": 20,
								"sectionItemType": "field",
								"startCol": 0
							},
							{
								"dropEffect": "move",
								"endCol": 2,
								"fieldId": "attachment",
								"height": 53,
								"id": "28c7bc10-a789-11ed-b669-f1c6817aceab",
								"index": 21,
								"listId": "caseinfoid-6cdd9d40-a787-11ed-b669-f1c6817aceab",
								"sectionItemType": "field",
								"startCol": 0
							}
						],
						"maxW": 3,
						"minH": 1,
						"moved": false,
						"name": "Closing Information",
						"static": false,
						"w": 3,
						"x": 0,
						"y": 10
					},
					{
						"displayType": "ROW",
						"h": 4,
						"hideName": false,
						"i": "ksqmpk4toz-caseinfoid-ksqmpk4toz-caseinfoid-ksqmpk4toz-caseinfoid-47bdaea0-a7a1-11ed-b980-a9b1848be7e5",
						"items": [
							{
								"endCol": 4,
								"fieldId": "gracase",
								"height": 22,
								"id": "34bcea90-a7a2-11ed-b980-a9b1848be7e5",
								"index": 0,
								"sectionItemType": "field",
								"startCol": 0
							},
							{
								"endCol": 2,
								"fieldId": "gracaseentity",
								"height": 22,
								"id": "831363e0-a7a2-11ed-b980-a9b1848be7e5",
								"index": 1,
								"sectionItemType": "field",
								"startCol": 0
							},
							{
								"dropEffect": "move",
								"endCol": 2,
								"fieldId": "gracaseentityid",
								"height": 22,
								"id": "84a32ba0-a7a2-11ed-b980-a9b1848be7e5",
								"index": 2,
								"listId": "caseinfoid-47bdaea0-a7a1-11ed-b980-a9b1848be7e5",
								"sectionItemType": "field",
								"startCol": 0
							},
							{
								"endCol": 2,
								"fieldId": "gracaseentitytypeid",
								"height": 22,
								"id": "a661e600-b28d-11ed-8102-cbfcd5838b40",
								"index": 3,
								"sectionItemType": "field",
								"startCol": 0
							},
							{
								"dropEffect": "move",
								"endCol": 2,
								"fieldId": "gracaseownername",
								"height": 22,
								"id": "f4772430-a7a3-11ed-b980-a9b1848be7e5",
								"index": 4,
								"listId": "caseinfoid-47bdaea0-a7a1-11ed-b980-a9b1848be7e5",
								"sectionItemType": "field",
								"startCol": 0
							},
							{
								"dropEffect": "move",
								"endCol": 2,
								"fieldId": "gracaseopendate",
								"height": 22,
								"id": "38b8b3d0-a7a3-11ed-b980-a9b1848be7e5",
								"index": 5,
								"listId": "caseinfoid-47bdaea0-a7a1-11ed-b980-a9b1848be7e5",
								"sectionItemType": "field",
								"startCol": 0
							},
							{
								"endCol": 2,
								"fieldId": "gracaseriskdate",
								"height": 22,
								"id": "53818b60-a7a3-11ed-b980-a9b1848be7e5",
								"index": 6,
								"sectionItemType": "field",
								"startCol": 0
							},
							{
								"dropEffect": "move",
								"endCol": 2,
								"fieldId": "gracaseriskscore",
								"height": 22,
								"id": "6fb69290-a7a2-11ed-b980-a9b1848be7e5",
								"index": 7,
								"listId": "caseinfoid-47bdaea0-a7a1-11ed-b980-a9b1848be7e5",
								"sectionItemType": "field",
								"startCol": 0
							},
							{
								"endCol": 2,
								"fieldId": "gracasestatus",
								"height": 22,
								"id": "e8e6a190-a7a3-11ed-b980-a9b1848be7e5",
								"index": 8,
								"sectionItemType": "field",
								"startCol": 0
							},
							{
								"endCol": 2,
								"fieldId": "gracaseweblink",
								"height": 22,
								"id": "2470a2b0-a7a4-11ed-b980-a9b1848be7e5",
								"index": 9,
								"sectionItemType": "field",
								"startCol": 0
							},
							{
								"dropEffect": "move",
								"endCol": 4,
								"fieldId": "gracaseanomalydetails",
								"height": 106,
								"id": "57344510-a7a1-11ed-b980-a9b1848be7e5",
								"index": 10,
								"listId": "caseinfoid-47bdaea0-a7a1-11ed-b980-a9b1848be7e5",
								"sectionItemType": "field",
								"startCol": 0
							}
						],
						"maxW": 3,
						"minH": 1,
						"moved": false,
						"name": "GRA Alert details",
						"static": false,
						"w": 2,
						"x": 0,
						"y": 0
					},
					{
						"displayType": "ROW",
						"h": 4,
						"hideName": false,
						"i": "ksqmpk4toz-caseinfoid-ksqmpk4toz-caseinfoid-ksqmpk4toz-caseinfoid-3636efe0-a830-11ed-9cf5-7d242b23291a",
						"items": [
							{
								"endCol": 2,
								"fieldId": "owner",
								"height": 22,
								"id": "482e3dc0-a830-11ed-9cf5-7d242b23291a",
								"index": 0,
								"sectionItemType": "field",
								"startCol": 0
							},
							{
								"endCol": 2,
								"fieldId": "shift",
								"height": 22,
								"id": "4e037760-a830-11ed-9cf5-7d242b23291a",
								"index": 1,
								"sectionItemType": "field",
								"startCol": 0
							},
							{
								"endCol": 2,
								"fieldId": "severity",
								"height": 22,
								"id": "6352f0f0-a830-11ed-9cf5-7d242b23291a",
								"index": 2,
								"sectionItemType": "field",
								"startCol": 0
							},
							{
								"dropEffect": "move",
								"endCol": 2,
								"fieldId": "dbotcreated",
								"height": 22,
								"id": "2dba8890-b82a-11ed-bc9f-d7ff24e1c825",
								"index": 3,
								"listId": "caseinfoid-ksqmpk4toz-caseinfoid-3636efe0-a830-11ed-9cf5-7d242b23291a",
								"sectionItemType": "field",
								"startCol": 0
							},
							{
								"endCol": 2,
								"fieldId": "occurred",
								"height": 22,
								"id": "693ee6e0-a830-11ed-9cf5-7d242b23291a",
								"index": 4,
								"sectionItemType": "field",
								"startCol": 0
							},
							{
								"endCol": 2,
								"fieldId": "closetime",
								"height": 22,
								"id": "700a6760-a830-11ed-9cf5-7d242b23291a",
								"index": 5,
								"sectionItemType": "field",
								"startCol": 0
							},
							{
								"dropEffect": "move",
								"endCol": 2,
								"fieldId": "acknowledgementsla",
								"height": 22,
								"id": "9f7e1410-a830-11ed-9cf5-7d242b23291a",
								"index": 6,
								"listId": "caseinfoid-ksqmpk4toz-caseinfoid-ksqmpk4toz-caseinfoid-3636efe0-a830-11ed-9cf5-7d242b23291a",
								"sectionItemType": "field",
								"startCol": 0
							},
							{
								"endCol": 2,
								"fieldId": "detectionsla",
								"height": 22,
								"id": "86906520-a830-11ed-9cf5-7d242b23291a",
								"index": 7,
								"sectionItemType": "field",
								"startCol": 0
							},
							{
								"endCol": 2,
								"fieldId": "mitigationsla",
								"height": 22,
								"id": "8d4cf180-a830-11ed-9cf5-7d242b23291a",
								"index": 8,
								"sectionItemType": "field",
								"startCol": 0
							},
							{
								"endCol": 2,
								"fieldId": "closuresla",
								"height": 22,
								"id": "96732ae0-a830-11ed-9cf5-7d242b23291a",
								"index": 9,
								"sectionItemType": "field",
								"startCol": 0
							},
							{
								"endCol": 2,
								"fieldId": "threatresponsesla",
								"height": 22,
								"id": "ab43d780-a830-11ed-9cf5-7d242b23291a",
								"index": 10,
								"sectionItemType": "field",
								"startCol": 0
							}
						],
						"maxW": 3,
						"minH": 1,
						"moved": false,
						"name": "Case details ",
						"static": false,
						"w": 1,
						"x": 2,
						"y": 0
					}
				],
				"type": "custom"
			},
			{
				"id": "warRoom",
				"mobileHidden": false,
				"name": "War Room",
				"readOnly": false,
				"roles": [
					"CSOC-XSOAR-Architect",
					"Administrator"
				],
				"type": "warRoom",
				"webHidden": false
			},
			{
				"id": "workPlan",
				"mobileHidden": false,
				"name": "Work Plan",
				"readOnly": false,
				"roles": [
					"CSOC_Demisto_Admin",
					"Administrator",
					"CSOC-XSOAR-Architect"
				],
				"type": "workPlan",
				"webHidden": false
			},
			{
				"id": "evidenceBoard",
				"name": "Evidence Board",
				"type": "evidenceBoard"
			},
			{
				"id": "relatedIncidents",
				"name": "Related Incidents",
				"type": "relatedIncidents"
			},
			{
				"id": "canvas",
				"name": "Canvas",
				"type": "canvas"
			}
		]
	},
	"edit": {
		"sections": [
			{
				"description": "",
				"fields": [
					{
						"fieldId": "incident_name",
						"isVisible": true
					},
					{
						"fieldId": "incident_type",
						"isVisible": true
					},
					{
						"fieldId": "incident_severity",
						"isVisible": true
					},
					{
						"fieldId": "incident_occurred",
						"isVisible": true
					},
					{
						"fieldId": "incident_details",
						"isVisible": true
					},
					{
						"fieldId": "incident_attachment",
						"isVisible": true
					},
					{
						"fieldId": "incident_labels",
						"isVisible": true
					}
				],
				"isVisible": true,
				"name": "Basic Information",
				"query": null,
				"queryType": "",
				"readOnly": false,
				"type": ""
			}
		]
	},
	"fromServerVersion": "",
	"group": "incident",
	"id": "0486006a-f9b7-4168-8e41-8d6d00fb2f99",
	"indicatorsDetails": null,
	"indicatorsQuickView": null,
	"itemVersion": "",
	"locked": false,
	"mobile": null,
	"name": "GRA Alert Layout",
	"packID": "",
	"packName": "",
	"propagationLabels": [
		"all"
	],
	"quickView": null,
	"quickViewV2": null,
	"system": false,
	"toServerVersion": "",
	"version": -1
}