{
	"allRead": true,
	"allReadWrite": true,
	"cacheVersn": 0,
	"data": "[{\"assigned\":8,\"name\":\"Counter\",\"role\":\"indexing\",\"scan\":0,\"seniorl1\":15},{\"assigned\":[\"1490504\",\"1490520\",\"1490549\",\"1490566\",\"1490596\",\"1490637\",\"1490665\",\"1490687\",\"1490703\",\"1490719\",\"1490739\",\"1490753\",\"1490774\"],\"condition\":\"Perfect\",\"name\":\"Akash Jajugar\",\"role\":\"L1\"},{\"assigned\":[\"1490507\",\"1490515\",\"1490550\",\"1490569\",\"1490599\",\"1490643\",\"1490667\",\"1490688\",\"1490704\",\"1490720\",\"1490741\",\"1490754\",\"1490777\"],\"condition\":\"Perfect\",\"name\":\"Appala Edala\",\"role\":\"L1\"},{\"assigned\":[\"1490508\",\"1490528\",\"1490551\",\"1490570\",\"1490603\",\"1490646\",\"1490668\",\"1490689\",\"1490705\",\"1490721\",\"1490742\",\"1490755\",\"1490778\"],\"condition\":\"Perfect\",\"name\":\"Chabolu Sri Harshitha\",\"role\":\"L1\"},{\"assigned\":[\"1490522\"],\"condition\":\"Leave\",\"name\":\"Dinesh K\",\"role\":\"Senior\"},{\"assigned\":[\"1490510\",\"1490523\"],\"condition\":\"Leave\",\"name\":\"Ghouse Dudekula\",\"role\":\"L1\"},{\"assigned\":[\"1490511\",\"1490529\",\"1490552\",\"1490572\",\"1490607\",\"1490647\",\"1490671\",\"1490691\",\"1490708\",\"1490724\",\"1490744\",\"1490757\",\"1490779\"],\"condition\":\"Perfect\",\"name\":\"Krishna D\",\"role\":\"L1\"},{\"assigned\":[\"1490512\",\"1490530\",\"1490553\",\"1490573\",\"1490612\",\"1490650\",\"1490672\",\"1490694\",\"1490710\",\"1490730\",\"1490745\",\"1490761\",\"1490782\"],\"condition\":\"Perfect\",\"name\":\"Mahesh Muramulla\",\"role\":\"L1\"},{\"assigned\":[\"1490514\",\"1490535\",\"1490556\",\"1490575\",\"1490613\",\"1490651\",\"1490675\",\"1490695\",\"1490711\",\"1490731\",\"1490746\",\"1490762\",\"1490783\"],\"condition\":\"Perfect\",\"name\":\"Maheshwari Patil\",\"role\":\"L1\"},{\"assigned\":[],\"condition\":\"Perfect\",\"name\":\"Maunika Gujari\",\"role\":\"OPLead\"},{\"assigned\":[\"1490519\"],\"condition\":\"Leave\",\"name\":\"Pranav Lokhande\",\"role\":\"L1\"},{\"assigned\":[\"1490518\",\"1490539\",\"1490557\",\"1490576\",\"1490614\",\"1490653\",\"1490676\",\"1490697\",\"1490714\",\"1490732\",\"1490747\",\"1490767\"],\"condition\":\"Perfect\",\"name\":\"Rajasekhar Reddy Pamuri\",\"role\":\"L1\"},{\"assigned\":[\"1490534\",\"1490538\",\"1490584\",\"1490610\",\"1490649\",\"1490693\",\"1490696\"],\"condition\":\"Perfect\",\"name\":\"Rohit Borse\",\"role\":\"Senior\"},{\"assigned\":[\"1490517\",\"1490540\",\"1490559\"],\"condition\":\"Leave\",\"name\":\"SHARANYA KOTHALIL\",\"role\":\"L1\"},{\"assigned\":[\"1490521\",\"1490543\",\"1490560\",\"1490577\",\"1490615\",\"1490657\",\"1490678\",\"1490698\",\"1490715\",\"1490733\",\"1490748\",\"1490766\"],\"condition\":\"Perfect\",\"name\":\"Sai Kollipara\",\"role\":\"L1\"},{\"assigned\":[\"1490533\",\"1490580\",\"1490594\",\"1490645\",\"1490677\",\"1490692\",\"1490690\"],\"condition\":\"Perfect\",\"name\":\"Sakshi Pawar\",\"role\":\"Senior\"},{\"assigned\":[\"1490516\",\"1490544\",\"1490562\",\"1490583\",\"1490619\",\"1490658\",\"1490684\",\"1490700\",\"1490716\",\"1490734\",\"1490749\",\"1490768\"],\"condition\":\"Perfect\",\"name\":\"Swinal Patil\",\"role\":\"L1\"},{\"assigned\":[],\"condition\":\"Perfect\",\"name\":\"VOLLEPU SYAM KUMAR\",\"role\":\"Mail\"},{\"assigned\":[\"1490524\",\"1490546\",\"1490565\",\"1490585\",\"1490620\",\"1490662\",\"1490683\",\"1490701\",\"1490717\",\"1490736\",\"1490750\",\"1490772\"],\"condition\":\"Perfect\",\"name\":\"Vijaya Challagali\",\"role\":\"L1\"},{\"assigned\":[\"1490513\",\"1490547\",\"1490567\",\"1490586\",\"1490636\",\"1490661\",\"1490686\",\"1490702\",\"1490718\",\"1490738\",\"1490751\",\"1490773\"],\"condition\":\"Perfect\",\"name\":\"Yaswanth Kumar Vidigotti\",\"role\":\"L1\"}]",
	"definitionId": "",
	"description": "",
	"detached": false,
	"fromServerVersion": "",
	"id": "Operators Profile",
	"itemVersion": "",
	"locked": false,
	"name": "Operators Profile",
	"nameLocked": false,
	"packID": "",
	"packName": "",
	"previousAllRead": true,
	"previousAllReadWrite": true,
	"propagationLabels": [
		"all"
	],
	"system": false,
	"tags": null,
	"toServerVersion": "",
	"truncated": false,
	"type": "plain_text",
	"version": -1
}