{
	"allRead": true,
	"allReadWrite": true,
	"cacheVersn": 0,
	"data": "mitreid,score\nTA0043 - Reconnaissance, 1\nTA0042 - Resource Development, 1\nTA0001 - Initial Access, 1\nTA0002 - Execution, 2\nTA0003 - Persistence, 3\nTA0004 - Privilege Escalation, 3\nTA0005 - Defense Evasion, 3\nTA0006 - Credential Access, 3\nTA0007 - Discovery, 3\nTA0008 - Lateral Movement, 4\nTA0009 - Collection,4\nTA0011 - Command and Control, 5\nTA0010 - Exfiltration, 6\nTA0040 - Impact, 6",
	"definitionId": "",
	"description": "",
	"detached": false,
	"fromServerVersion": "",
	"id": "mitretacticsscore",
	"itemVersion": "",
	"locked": false,
	"name": "mitretacticsscore",
	"nameLocked": false,
	"packID": "",
	"packName": "",
	"previousAllRead": true,
	"previousAllReadWrite": true,
	"propagationLabels": [
		"all"
	],
	"system": false,
	"tags": null,
	"toServerVersion": "",
	"truncated": false,
	"type": "plain_text",
	"version": -1
}