{
	"allRead": true,
	"allReadWrite": true,
	"cacheVersn": 0,
	"data": " {\n   \"10004\":{\n      \"byoiintegrations\":\"\",\n      \"customercomments\":\"None\",\n      \"enrichmentintegrations\":[\n         \"ServiceNow v2\",\n         \"Cortex XDR - IOC\",\n         \"ServiceNow (Deprecated)\"\n      ],\n      \"mainintegration\":\"ServiceNow\",\n      \"operationalintegrations\":[\n         \"Active Directory Query v2\",\n         \"ServiceNow IAM\",\n         \"Cortex XDR - XQL Query Engine\"\n      ],\n      \"panwcomments\":\"None\",\n      \"tags\":\"Malware\",\n      \"usecasedescription\":\"Use case Desc\",\n      \"usecasedocumenturl\":\"https://google.com\",\n      \"usecasename\":\"Use Case 1\",\n      \"usecasenumber\":\"10004\"\n   },\n   \"10013\":{\n      \"byoiintegrations\":\"\",\n      \"customercomments\":\"None\",\n      \"enrichmentintegrations\":[\n         \"Palo Alto Networks PAN-OS\",\n         \"ServiceNow IAM\",\n         \"ServiceNow CMDB\"\n      ],\n      \"mainintegration\":\"ServiceNowV2\",\n      \"operationalintegrations\":[\n         \"Palo Alto Networks PAN-OS\",\n         \"ServiceNow IAM\",\n         \"ServiceNow v2\"\n      ],\n      \"panwcomments\":\"None\",\n      \"tags\":\"Proxy\",\n      \"usecasedescription\":\"Use case Desc\",\n      \"usecasedocumenturl\":\"https://google.com\",\n      \"usecasename\":\"Use case 3\",\n      \"usecasenumber\":\"10013\"\n   },\n   \"10014\":{\n      \"byoiintegrations\":\"\",\n      \"customercomments\":\"None\",\n      \"enrichmentintegrations\":[\n         \"Palo Alto Networks PAN-OS\",\n         \"ServiceNow IAM\"\n      ],\n      \"mainintegration\":\"ActiveDirectoryV2\",\n      \"operationalintegrations\":[\n         \"Palo Alto Networks PAN-OS\",\n         \"ServiceNow IAM\"\n      ],\n      \"panwcomments\":\"None\",\n      \"tags\":\"Proxy\",\n      \"usecasedescription\":\"Use case Desc\",\n      \"usecasedocumenturl\":\"https://google.com\",\n      \"usecasename\":\"Use case 3\",\n      \"usecasenumber\":\"10013\"\n   },\n   \"locked\":\"0\"\n}\n",
	"definitionId": "",
	"description": "",
	"detached": false,
	"fromServerVersion": "",
	"id": "UsecaseAdoptionList",
	"itemVersion": "",
	"locked": false,
	"name": "UsecaseAdoptionList",
	"nameLocked": false,
	"packID": "",
	"packName": "",
	"previousAllRead": true,
	"previousAllReadWrite": true,
	"propagationLabels": [
		"all"
	],
	"system": false,
	"tags": null,
	"toServerVersion": "",
	"truncated": false,
	"type": "json",
	"version": -1
}