{
	"action": "script",
	"cacheVersn": 0,
	"definitionId": "",
	"enabled": false,
	"existingEventsFilters": [],
	"fromServerVersion": "",
	"id": "866e3c5e-cfaa-4039-8db1-faae44e04839",
	"index": 21,
	"itemVersion": "",
	"linkTo": "oldest",
	"locked": false,
	"name": "Link Duplicate CrowdStrike Incidents",
	"newEventFilters": [
		[
			{
				"left": {
					"isContext": true,
					"value": {
						"simple": "type"
					}
				},
				"operator": "isEqualString",
				"right": {
					"isContext": false,
					"value": {
						"simple": "Malware Investigation"
					}
				},
				"type": "singleSelect"
			}
		]
	],
	"packID": "",
	"packName": "",
	"period": {
		"by": "hours",
		"fromValue": 12
	},
	"propagationLabels": [
		"all"
	],
	"readyExistingEventsFilters": [],
	"readyNewEventFilters": [
		[
			{
				"left": {
					"isContext": true,
					"value": {
						"simple": "type"
					}
				},
				"operator": "isEqualString",
				"right": {
					"isContext": false,
					"value": {
						"simple": "Malware Investigation"
					}
				},
				"type": "singleSelect"
			}
		]
	],
	"scriptID": "fea4a899-f39a-4f4e-8fad-9bf4dc3ea570",
	"scriptName": "",
	"searchClosed": true,
	"system": false,
	"toServerVersion": "",
	"version": -1
}