{
	"cacheVersn": 0,
	"contextPath": "",
	"contextValue": "",
	"defaultMapping": null,
	"definitionId": "",
	"details": "Internal IP",
	"disabled": false,
	"enhancementScriptNames": [],
	"excludedBrands": [],
	"expiration": 0,
	"file": false,
	"fileHashesPriority": null,
	"formatScript": "UnEscapeIPs",
	"fromServerVersion": "",
	"id": "f9996588-9e68-4563-8b8f-9d60fff5eae4",
	"itemVersion": "",
	"layout": "",
	"legacyNames": null,
	"locked": false,
	"manualMapping": {},
	"mergeContext": false,
	"packID": "",
	"packName": "",
	"propagationLabels": [
		"all"
	],
	"regex": "(10((?:\\[\\.\\]|\\.)(25[0-5]|2[0-4][0-9]|1[0-9]{1,2}|[0-9]{1,2})){3}|((172(?:\\[\\.\\]|\\.)(1[6-9]|2[0-9]|3[01]))|192(?:\\[\\.\\]|\\.)168)((?:\\[\\.\\]|\\.)(25[0-5]|2[0-4][0-9]|1[0-9]{1,2}|[0-9]{1,2})){2})",
	"reputationCommand": "",
	"reputationScriptName": "",
	"shouldShareComments": false,
	"system": false,
	"toServerVersion": "",
	"updateAfter": 0,
	"version": -1
}