{
	"cacheVersn": 0,
	"contextPath": "",
	"contextValue": "",
	"defaultMapping": null,
	"definitionId": "",
	"details": "Cryptocurrency Address",
	"disabled": false,
	"enhancementScriptNames": null,
	"excludedBrands": null,
	"expiration": 0,
	"file": false,
	"fileHashesPriority": null,
	"formatScript": "CryptoCurrenciesFormat",
	"fromServerVersion": "5.0.0",
	"id": "Cryptocurrency Address",
	"itemVersion": "1.1.55",
	"layout": "Cryptocurrency",
	"legacyNames": null,
	"locked": false,
	"manualMapping": {
		"cryptocurrencyaddresstype": {
			"simple": "Cryptocurrency.AddressType"
		}
	},
	"mergeContext": false,
	"packID": "Cryptocurrency",
	"packName": "Cryptocurrency",
	"packPropagationLabels": [
		"all"
	],
	"propagationLabels": [],
	"regex": "\\b[13][a-km-zA-HJ-NP-Z1-9]{25,34}\\b",
	"reputationCommand": "crypto",
	"reputationScriptName": "",
	"shouldShareComments": false,
	"system": true,
	"toServerVersion": "",
	"updateAfter": 0,
	"version": -1
}