{
	"cacheVersn": 0,
	"contextPath": "",
	"contextValue": "",
	"defaultMapping": null,
	"definitionId": "",
	"details": "File SHA1",
	"disabled": false,
	"enhancementScriptNames": [
		"FileReputation"
	],
	"excludedBrands": [
		"Recorded Future v2.1"
	],
	"expiration": 0,
	"file": false,
	"fileHashesPriority": null,
	"formatScript": "",
	"fromServerVersion": "",
	"id": "d8482bba-55ac-4c83-8c3c-3fcd49296f8f",
	"itemVersion": "",
	"layout": "",
	"legacyNames": null,
	"locked": false,
	"manualMapping": {},
	"mergeContext": false,
	"packID": "",
	"packName": "",
	"propagationLabels": [
		"all"
	],
	"regex": "\\b[a-fA-F\\d]{40}\\b",
	"reputationCommand": "file",
	"reputationScriptName": "",
	"shouldShareComments": false,
	"system": false,
	"toServerVersion": "",
	"updateAfter": 0,
	"version": -1
}