{
	"Cache": null,
	"cacheVersn": 0,
	"category": "",
	"dataType": "incidents",
	"dateRange": {
		"fromDate": "0001-01-01T00:00:00Z",
		"fromDateLicense": "0001-01-01T00:00:00Z",
		"period": {
			"by": "",
			"byFrom": "days",
			"byTo": "",
			"field": "",
			"fromValue": 0,
			"toValue": null
		},
		"toDate": "0001-01-01T00:00:00Z"
	},
	"definitionId": "",
	"fromServerVersion": "5.0.0",
	"id": "9dc1ea63-156d-45d4-8da7-d180d63ad4f6",
	"isPredefined": false,
	"itemVersion": "1.2.7",
	"name": "CS Cases without attachments",
	"packID": "",
	"packName": "",
	"params": {
		"groupBy": [
			"owner"
		],
		"valuesFormat": "abbreviated"
	},
	"propagationLabels": [
		"all"
	],
	"query": "type:\"Malware Investigation\" and attachmentid:\"\" and status:Closed and -closeReason:Duplicate",
	"size": 70,
	"toServerVersion": "",
	"version": -1,
	"widgetType": "pie"
}